{
  "slack_channel": "C0ASR4NFLPR",
  "sources": [
    {"name": "Politico - Congress", "url": "https://rss.politico.com/congress.xml"},
    {"name": "Politico - Politics", "url": "https://rss.politico.com/politics-news.xml"},
    {"name": "Politico - Defense", "url": "https://rss.politico.com/defense.xml"},
    {"name": "Politico - Morning Tech", "url": "https://rss.politico.com/morningtech.xml"},
    {"name": "The Hill - News", "url": "https://thehill.com/news/feed/"},
    {"name": "The Hill - Technology", "url": "https://thehill.com/policy/technology/feed/"},
    {"name": "The Hill - Finance", "url": "https://thehill.com/business/feed/"},
    {"name": "The Hill - Defense", "url": "https://thehill.com/policy/defense/feed/"},
    {"name": "Axios", "url": "https://www.axios.com/feeds/feed.rss"},
    {"name": "Semafor", "url": "https://semafor.com/rss.xml"},
    {"name": "Roll Call", "url": "https://www.rollcall.com/feed/"},
    {"name": "CoinDesk", "url": "https://www.coindesk.com/arc/outboundfeeds/rss/"},
    {"name": "The Block", "url": "https://www.theblock.co/rss.xml"},
    {"name": "Wired", "url": "https://www.wired.com/feed/rss"},
    {"name": "Breaking Defense", "url": "https://breakingdefense.com/feed/"},
    {"name": "Defense One", "url": "https://defenseone.com/rss/all"},
    {"name": "Defense News", "url": "https://www.defensenews.com/arc/outboundfeeds/rss/"},
    {"name": "Nextgov/FCW", "url": "https://www.nextgov.com/rss/all/"},
    {"name": "Reuters", "url": "https://www.reutersagency.com/feed/"},
    {"name": "Washington Post - Politics", "url": "https://feeds.washingtonpost.com/rss/politics"},
    {"name": "New York Times - Politics", "url": "https://rss.nytimes.com/services/xml/rss/nyt/Politics.xml"},
    {"name": "Associated Press", "url": "https://rsshub.app/apnews/topics/politics"},
    {"name": "Wall Street Journal", "url": "https://feeds.a.dj.com/rss/RSSWorldNews.xml"},
    {"name": "Financial Times", "url": "https://www.ft.com/rss/home"}
  ]
}
